pybear/__init__.py
pybear/_version.py
pybear/base/_DictMenuPrint.py
pybear/base/__init__.py
pybear/base/__type_aliases.py
pybear/base/_cast_to_ndarray.py
pybear/base/_check_1D_num_sequence.py
pybear/base/_check_1D_str_sequence.py
pybear/base/_check_2D_num_array.py
pybear/base/_check_2D_str_array.py
pybear/base/_check_dtype.py
pybear/base/_check_feature_names.py
pybear/base/_check_is_finite.py
pybear/base/_check_is_fitted.py
pybear/base/_check_n_features.py
pybear/base/_check_scipy_sparse.py
pybear/base/_check_shape.py
pybear/base/_copy_X.py
pybear/base/_ensure_2D.py
pybear/base/_get_feature_names.py
pybear/base/_get_feature_names_out.py
pybear/base/_is_fitted.py
pybear/base/_num_features.py
pybear/base/_num_samples.py
pybear/base/_set_order.py
pybear/base/_validate_data.py
pybear/base/_validate_user_input.py
pybear/base/exceptions/__init__.py
pybear/base/exceptions/_exceptions.py
pybear/base/mixins/_FeatureMixin.py
pybear/base/mixins/_FileDumpMixin.py
pybear/base/mixins/_FitTransformMixin.py
pybear/base/mixins/_GetParamsMixin.py
pybear/base/mixins/_ReprMixin.py
pybear/base/mixins/_SetOutputMixin.py
pybear/base/mixins/_SetParamsMixin.py
pybear/base/mixins/__init__.py
pybear/feature_extraction/__init__.py
pybear/feature_extraction/text/WORDS_TO_DISPOSITION
pybear/feature_extraction/text/_AutoTextCleaner/AutoTextCleaner.py
pybear/feature_extraction/text/_AutoTextCleaner/__init__.py
pybear/feature_extraction/text/_AutoTextCleaner/_type_aliases.py
pybear/feature_extraction/text/_AutoTextCleaner/_validation/__init__.py
pybear/feature_extraction/text/_AutoTextCleaner/_validation/_get_statistics.py
pybear/feature_extraction/text/_AutoTextCleaner/_validation/_lexicon_lookup.py
pybear/feature_extraction/text/_AutoTextCleaner/_validation/_ngram_merge.py
pybear/feature_extraction/text/_AutoTextCleaner/_validation/_remove.py
pybear/feature_extraction/text/_AutoTextCleaner/_validation/_replace.py
pybear/feature_extraction/text/_AutoTextCleaner/_validation/_return_dim.py
pybear-0.2.3.dist-info/METADATA
pybear-0.2.3.dist-info/WHEEL
pybear-0.2.3.dist-info/licenses/LICENSE
pybear-0.2.3.dist-info/RECORD
