Metadata-Version: 2.4
Name: pybear
Version: 0.2.3
Summary: Python modules for miscellaneous data analytics applications
License: BSD-3-Clause
License-File: LICENSE
Keywords: python data analytics scikit-API text
Author: Bill Sousa
Author-email: WKSJR99@msn.com
Maintainer: Bill Sousa
Requires-Python: >=3.10
Classifier: License :: OSI Approved :: BSD License
Classifier: Programming Language :: Python :: 3
Classifier: Programming Language :: Python :: 3.10
Classifier: Programming Language :: Python :: 3.11
Classifier: Programming Language :: Python :: 3.12
Classifier: Programming Language :: Python :: 3.13
Classifier: Programming Language :: Python :: 3.14
Requires-Dist: joblib (>=1.3.0)
Requires-Dist: numpy (>=2.1.0)
Requires-Dist: pandas (>=2.2.3)
Requires-Dist: polars (>=1.19.0)
Requires-Dist: psutil (>=5.7.0)
Requires-Dist: scikit-learn (>=1.5.2)
Requires-Dist: scipy (>=1.15.0)
Requires-Dist: typing_extensions (>=4.12.0)
Project-URL: Documentation, https://pybear.readthedocs.io/en/stable/
Project-URL: Homepage, https://github.com/PylarBear/pybear
Project-URL: Repository, https://github.com/PylarBear/pybear
